{
  "run_id": "20260609_164219_de565d00",
  "started_at": "2026-06-09T16:42:19+08:00",
  "completed_at": "2026-06-09T16:46:00+08:00",
  "tasks": 156,
  "accepted": 53,
  "rejected": 103,
  "review": 0,
  "gaps": 103,
  "recrawl_rows": [
    2,
    5,
    8,
    11,
    15,
    17
  ],
  "recrawl_performed": true,
  "online_ai": true,
  "node_events": [
    "[数据整理][证据接收] 读取 157 条原始指标证据，复用 36 条缓存判断。",
    "[数据整理][来源分类] 完成来源分级：commercial 2、official 95、public 60。",
    "[数据整理][事实抽取] 形成 157 条候选事实；新增抽取 121 条，缓存复用 36 条。",
    "[数据整理][主体校验] 主体与指标归属校验完成，预拒绝 52 条。",
    "[数据整理][质量审计] 通过 50 条、待复核 0 条、拒绝 107 条。",
    "[数据整理][冲突仲裁] 检查 50 组事实，发现 0 组冲突。",
    "[数据整理][缺口规划] 识别 107 个事实缺口，安排 6 个定向补爬行。",
    "[数据整理][定向补爬] 完成行 2, 5, 8, 11, 15, 17 的补爬，重新进入整理流程。",
    "[数据整理][证据接收] 读取 156 条原始指标证据，复用 27 条缓存判断。",
    "[数据整理][来源分类] 完成来源分级：commercial 2、official 94、public 60。",
    "[数据整理][事实抽取] 形成 156 条候选事实；新增抽取 129 条，缓存复用 27 条。",
    "[数据整理][主体校验] 主体与指标归属校验完成，预拒绝 64 条。",
    "[数据整理][质量审计] 通过 53 条、待复核 0 条、拒绝 103 条。",
    "[数据整理][冲突仲裁] 检查 53 组事实，发现 0 组冲突。",
    "[数据整理][缺口规划] 识别 103 个事实缺口，安排 0 个定向补爬行。",
    "[数据整理][发布] 发布层写入 53 条，拒绝 103 条，待人工复核 0 条。",
    "[数据整理][缓存保护] 保留上一轮更高质量事实 20 条，避免本轮离线/补爬退化覆盖。"
  ],
  "extra": {
    "preserved_previous_facts": 20,
    "protected_semantic_keys": [
      "1O1O|5G-A|row_4",
      "1O1O|漫游|row_3",
      "3HK|促销折扣|row_6",
      "3HK|漫游|row_6",
      "HKT|净利润|row_2",
      "HKT|资费|row_3",
      "Hutchison|ARPU|row_5",
      "Hutchison|EBITDA|row_5",
      "Hutchison|净利润|row_5",
      "Hutchison|服务收入|row_5",
      "Hutchison|派息|row_5",
      "Hutchison|运营收入/总收益|row_5",
      "SmarTone|EBITDA|row_8",
      "SmarTone|服务收入|row_8",
      "中国联通|5G-A|row_21",
      "中国联通|DICT|row_21",
      "中国联通|资本开支|row_21",
      "行业资讯|前沿产品|row_31",
      "通信监管机构|卫星通信|row_28",
      "通信监管机构|覆盖义务|row_28"
    ],
    "cache_backup": "curation_data/cache_backups/20260609_164219_de565d00_before_publish.json",
    "agent_trace": "curation_data/agent_trace.jsonl"
  }
}